opendmxadapter/__init__.py
opendmxadapter/adapter.py
opendmxadapter/fixtures/__init__.py
opendmxadapter/fixtures/basefixture.py
opendmxadapter/fixtures/cameo/__init__.py
opendmxadapter/fixtures/cameo/rootpar6.py
opendmxadapter/fixtures/eurolite/__init__.py
opendmxadapter/fixtures/eurolite/tmhx4.py
opendmxadapter/utils/__init__.py
opendmxadapter/utils/helper.py
opendmxadapter-1.0.2.post1.dist-info/METADATA
opendmxadapter-1.0.2.post1.dist-info/WHEEL
opendmxadapter-1.0.2.post1.dist-info/licenses/LICENSE
opendmxadapter-1.0.2.post1.dist-info/RECORD
