Metadata-Version: 2.4
Name: opendmxadapter
Version: 1.0.2.post1
Summary: Easy-to-use library to work with an OpenDMX controller
Project-URL: Homepage, https://github.com/Ari24-cb24/opendmxadapter
Project-URL: Issues, https://github.com/Ari24-cb24/opendmxadapter/issues
Author-email: Ari van Houten <ari.publicmail@gmail.com>
License-Expression: MIT
License-File: LICENSE
Classifier: Development Status :: 5 - Production/Stable
Classifier: Operating System :: OS Independent
Classifier: Programming Language :: Python :: 3
Classifier: Topic :: System :: Hardware :: Universal Serial Bus (USB)
Classifier: Typing :: Typed
Requires-Python: >=3.9
Requires-Dist: pyftdi>=0.56.0
Requires-Dist: pyserial>=3.5
